znu_nlp/__init__.py
znu_nlp/module_call.py
znu_nlp-0.0.3.dist-info/LICENSE
znu_nlp-0.0.3.dist-info/METADATA
znu_nlp-0.0.3.dist-info/WHEEL
znu_nlp-0.0.3.dist-info/top_level.txt
znu_nlp-0.0.3.dist-info/RECORD
